velaris_csm_access_kit/__init__.py
velaris_csm_access_kit/_version.py
velaris_csm_access_kit/cache.py
velaris_csm_access_kit/db.py
velaris_csm_access_kit/py.typed
velaris_csm_access_kit/secrets.py
velaris_csm_access_kit/service_registry.py
velaris_csm_access_kit/token.py
velaris_csm_access_kit-0.1.4.dist-info/METADATA
velaris_csm_access_kit-0.1.4.dist-info/WHEEL
velaris_csm_access_kit-0.1.4.dist-info/licenses/LICENSE
velaris_csm_access_kit-0.1.4.dist-info/RECORD
