Metadata-Version: 2.4
Name: velaris-csm-access-kit
Version: 0.1.4
Summary: A Python library providing authentication, caching, database connection pooling, service registry, and secrets management functionality for Velaris CSM applications
Project-URL: Homepage, https://github.com/velaris/velaris-csm-access-kit
Project-URL: Repository, https://github.com/velaris/velaris-csm-access-kit
Project-URL: Documentation, https://github.com/velaris/velaris-csm-access-kit#readme
Project-URL: Issues, https://github.com/velaris/velaris-csm-access-kit/issues
Author-email: Velaris <thilina.wickramaratne@velaris.io>
License-File: LICENSE
Keywords: authentication,aws,cache,csm,database,velaris
Classifier: Development Status :: 4 - Beta
Classifier: Intended Audience :: Developers
Classifier: License :: OSI Approved :: MIT License
Classifier: Programming Language :: Python :: 3
Classifier: Programming Language :: Python :: 3.8
Classifier: Programming Language :: Python :: 3.9
Classifier: Programming Language :: Python :: 3.10
Classifier: Programming Language :: Python :: 3.11
Classifier: Programming Language :: Python :: 3.12
Classifier: Programming Language :: Python :: 3.13
Classifier: Topic :: Software Development :: Libraries :: Python Modules
Classifier: Topic :: System :: Systems Administration :: Authentication/Directory
Requires-Python: >=3.8
Requires-Dist: boto3>=1.20.0
Requires-Dist: psycopg[pool]>=3.0.0
Requires-Dist: pyjwt>=2.0.0
Requires-Dist: requests>=2.25.0
Provides-Extra: dev
Requires-Dist: black>=22.0.0; extra == 'dev'
Requires-Dist: flake8>=4.0.0; extra == 'dev'
Requires-Dist: isort>=5.10.0; extra == 'dev'
Requires-Dist: mypy>=0.950; extra == 'dev'
Requires-Dist: pytest-asyncio>=0.21.0; extra == 'dev'
Requires-Dist: pytest>=7.0.0; extra == 'dev'
